iomotions/__init__.py
iomotions/event_emitter.py
iomotions/imotions.py
iomotions/otree/__init__.py
iomotions/otree/pages.py
iomotions/otree/_builtin/__init__.py
iomotions/unit_tests/__init__.py
iomotions/unit_tests/event_emitter_tests.py
iomotions-0.1.0.dist-info/LICENSE
iomotions-0.1.0.dist-info/METADATA
iomotions-0.1.0.dist-info/WHEEL
iomotions-0.1.0.dist-info/top_level.txt
iomotions-0.1.0.dist-info/RECORD
