Metadata-Version: 2.1
Name: iomotions
Version: 0.1.0
Summary: Utilities to interface with iMotions from oTree
Home-page: https://github.com/lochiego/iomotions
Author: Eric Gonzalez
Author-email: erigonz89@gmail.com
License: MIT License
Platform: UNKNOWN
Classifier: Programming Language :: Python :: 3
Classifier: License :: OSI Approved :: MIT License
Classifier: Operating System :: OS Independent
Requires-Python: >=3.6
License-File: LICENSE
